[   
    {
      "id": 1,
      "question": "Miles4Smiles",
      "answer":"Express",
      "options":["first","Express","Reactjs","Node js","JSX"],
      "level": "Hard"
    },
    {
        "id": 2,
        "question": "Miles4Smiles",
        "answer":"Second",
        "options":["Second","Express","Reactjs","Node js","JSX"],
        "level": "Hard"
    },
    {
        "id": 3,
        "question": "Miles4Smiles",
        "answer":"Third",
        "options":["Third","Express","Reactjs","Node js","JSX"],
        "level": "Moderate"
    },
    {
        "id": 4,
        "question": "Miles4Smiles",
        "answer":"Node js",
        "options":["forth","Express","Reactjs","Node js","JSX"],
        "level": "Moderate"
    },
    {
        "id": 5,
        "question": "Miles4Smiles",
        "answer":"JSX",
        "options":["fifth","Express","Reactjs","Node js","JSX"],
        "level": "Easy"
    },
    {
        "id": 6,
        "question": "Miles4Smiles",
        "answer":"Reactjs",
        "options":["MongoDB","Express","Reactjs","Node js","JSX"],
        "level": "Easy"
    }
  ]
  